[{"id":"0ac5c49c-01c0-42e0-89b1-bfd3f29a3885","title":"Lunch","amount":12.5,"category":"FOOD","date":[2025,4,21],"description":""},{"id":"1afda2b9-a80b-4842-9507-ffe7fbe182d8","title":"Movie Ticket","amount":12.0,"category":"ENTERTAINMENT","date":[2025,4,21],"description":""},{"id":"3b35271e-1033-45fb-9d1b-6d003dbe3746","title":"Gym Membership","amount":35.0,"category":"OTHER","date":[2025,4,21],"description":""},{"id":"6da02738-6445-4a29-bf23-9aebd0514755","title":"Coffee","amount":4.5,"category":"FOOD","date":[2025,4,21],"description":""},{"id":"c1fe0272-4fe6-48d9-9cbf-e50dd44595ff","title":"Bus Pass","amount":20.0,"category":"TRANSPORT","date":[2025,4,21],"description":""},{"id":"15d09180-72e5-46e4-a85a-cff07eef6e43","title":"Medicine","amount":15.99,"category":"OTHER","date":[2025,4,21],"description":""}]